Metadata-Version: 2.1
Name: tensornvme
Version: 0.1.0
Summary: A tensor disk offloader without data copying.
Home-page: UNKNOWN
License: Apache Software License 2.0
Platform: UNKNOWN
Classifier: Programming Language :: Python :: 3
Classifier: License :: OSI Approved :: Apache Software License
Classifier: Topic :: Scientific/Engineering :: Artificial Intelligence
Requires-Python: >=3.6
